<?xml version="1.0" ?>
<levels>
  <level id="1-2" action="remove" matches="2" squares="3">
    <![CDATA[
.-.-.\
| | |\
.-.-.\
| | |\
.-.-.\
    ]]>
  </level>
  <level id="1-4" action="move" matches="1" squares="2">
    <![CDATA[
.-.-.\
|   |\
.-.-.\
|   |\
.-.-.\
    ]]>
  </level>
  <level id="1-7" action="remove" matches="2" squares="2">
    <![CDATA[
.-.-.\
| | |\
.-.-.\
| |  \
.-.  \
    ]]>
  </level>
  <level id="1-13" action="remove" matches="2" squares="3">
    <![CDATA[
.-.    \
| |    \
.-.-.  \
| | |  \
. .-.-.\
|   | |\
.-.-.-.\
    ]]>
  </level>
  <level id="1-16" action="move" matches="2" squares="5">
    <![CDATA[
.-. .-.\
| | | |\
.-.-.-.\
  | |  \
.-.-. .\
| |    \
.-. . .\
    ]]>
  </level>
  <level id="1-19" action="add" matches="2" squares="4">
    <![CDATA[
.-.-.-.\
|     |\
.-. .-.\
| | | |\
. .-. .\
|     |\
.-.-.-.\
    ]]>
  </level>
  <level id="3-16" action="remove" matches="4" squares="4">
    <![CDATA[
.-.-.  \
|   |  \
.-.-.-.\
| | | |\
.-.-.-.\
| | | |\
.-.-.-.\
|   |  \
.-.-.  \
    ]]>
  </level>
</levels>
